rstudio_hpc/__init__.py
rstudio_hpc/cli.py
rstudio_hpc/rstudio_hpc.py
rstudio_hpc-0.1.0.dist-info/LICENSE
rstudio_hpc-0.1.0.dist-info/METADATA
rstudio_hpc-0.1.0.dist-info/WHEEL
rstudio_hpc-0.1.0.dist-info/entry_points.txt
rstudio_hpc-0.1.0.dist-info/RECORD
